setuptools_shim-0.0.2.dist-info/metadata.json
setuptools_shim-0.0.2.dist-info/DESCRIPTION.rst
setuptools_shim-0.0.2.dist-info/RECORD
setuptools_shim-0.0.2.dist-info/top_level.txt
setuptools_shim-0.0.2.dist-info/WHEEL
setuptools_shim-0.0.2.dist-info/METADATA
setuptools_shim-0.0.2.dist-info/pbr.json
setuptools_shim/main.py
setuptools_shim/frompip.py
setuptools_shim/__init__.py
setuptools_shim/shim.py
setuptools_shim/tests/test_setuptools_shim.py
setuptools_shim/tests/__init__.py
